// class version 59.0 (59)
// access flags 0x20
class HeapSort {

  // compiled from: HeapSort.java
  // access flags 0x19
  public final static INNERCLASS java/lang/invoke/MethodHandles$Lookup java/lang/invoke/MethodHandles Lookup

  // access flags 0x0
  <init>()V
   L0
    LINENUMBER 2 L0
    ALOAD 0
    INVOKESPECIAL java/lang/Object.<init> ()V
    RETURN
   L1
    LOCALVARIABLE this LHeapSort; L0 L1 0
    MAXSTACK = 1
    MAXLOCALS = 1

  // access flags 0x1
  public sort([I)V
   L0
    LINENUMBER 5 L0
    ALOAD 1
    ARRAYLENGTH
    ISTORE 2
   L1
    LINENUMBER 8 L1
    ILOAD 2
    ICONST_2
    IDIV
    ICONST_1
    ISUB
    ISTORE 3
   L2
   FRAME APPEND [I I]
    ILOAD 3
    IFLT L3
   L4
    LINENUMBER 9 L4
    ALOAD 0
    ALOAD 1
    ILOAD 2
    ILOAD 3
    INVOKEVIRTUAL HeapSort.heapify ([III)V
   L5
    LINENUMBER 8 L5
    IINC 3 -1
    GOTO L2
   L3
    LINENUMBER 12 L3
   FRAME CHOP 1
    ILOAD 2
    ICONST_1
    ISUB
    ISTORE 3
   L6
   FRAME APPEND [I]
    ILOAD 3
    IFLE L7
   L8
    LINENUMBER 14 L8
    ALOAD 1
    ICONST_0
    IALOAD
    ISTORE 4
   L9
    LINENUMBER 15 L9
    ALOAD 1
    ICONST_0
    ALOAD 1
    ILOAD 3
    IALOAD
    IASTORE
   L10
    LINENUMBER 16 L10
    ALOAD 1
    ILOAD 3
    ILOAD 4
    IASTORE
   L11
    LINENUMBER 19 L11
    ALOAD 0
    ALOAD 1
    ILOAD 3
    ICONST_0
    INVOKEVIRTUAL HeapSort.heapify ([III)V
   L12
    LINENUMBER 12 L12
    IINC 3 -1
    GOTO L6
   L7
    LINENUMBER 21 L7
   FRAME CHOP 1
    RETURN
   L13
    LOCALVARIABLE i I L2 L3 3
    LOCALVARIABLE temp I L9 L12 4
    LOCALVARIABLE i I L6 L7 3
    LOCALVARIABLE this LHeapSort; L0 L13 0
    LOCALVARIABLE arr [I L0 L13 1
    LOCALVARIABLE n I L1 L13 2
    MAXSTACK = 4
    MAXLOCALS = 5

  // access flags 0x0
  heapify([III)V
   L0
    LINENUMBER 27 L0
    ILOAD 3
    ISTORE 4
   L1
    LINENUMBER 28 L1
    ICONST_2
    ILOAD 3
    IMUL
    ICONST_1
    IADD
    ISTORE 5
   L2
    LINENUMBER 29 L2
    ICONST_2
    ILOAD 3
    IMUL
    ICONST_2
    IADD
    ISTORE 6
   L3
    LINENUMBER 32 L3
    ILOAD 5
    ILOAD 2
    IF_ICMPGE L4
    ALOAD 1
    ILOAD 5
    IALOAD
    ALOAD 1
    ILOAD 4
    IALOAD
    IF_ICMPLE L4
   L5
    LINENUMBER 33 L5
    ILOAD 5
    ISTORE 4
   L4
    LINENUMBER 36 L4
   FRAME APPEND [I I I]
    ILOAD 6
    ILOAD 2
    IF_ICMPGE L6
    ALOAD 1
    ILOAD 6
    IALOAD
    ALOAD 1
    ILOAD 4
    IALOAD
    IF_ICMPLE L6
   L7
    LINENUMBER 37 L7
    ILOAD 6
    ISTORE 4
   L6
    LINENUMBER 40 L6
   FRAME SAME
    ILOAD 4
    ILOAD 3
    IF_ICMPEQ L8
   L9
    LINENUMBER 41 L9
    ALOAD 1
    ILOAD 3
    IALOAD
    ISTORE 7
   L10
    LINENUMBER 42 L10
    ALOAD 1
    ILOAD 3
    ALOAD 1
    ILOAD 4
    IALOAD
    IASTORE
   L11
    LINENUMBER 43 L11
    ALOAD 1
    ILOAD 4
    ILOAD 7
    IASTORE
   L12
    LINENUMBER 46 L12
    ALOAD 0
    ALOAD 1
    ILOAD 2
    ILOAD 4
    INVOKEVIRTUAL HeapSort.heapify ([III)V
   L8
    LINENUMBER 48 L8
   FRAME SAME
    RETURN
   L13
    LOCALVARIABLE swap I L10 L8 7
    LOCALVARIABLE this LHeapSort; L0 L13 0
    LOCALVARIABLE arr [I L0 L13 1
    LOCALVARIABLE n I L0 L13 2
    LOCALVARIABLE i I L0 L13 3
    LOCALVARIABLE largest I L1 L13 4
    LOCALVARIABLE l I L2 L13 5
    LOCALVARIABLE r I L3 L13 6
    MAXSTACK = 4
    MAXLOCALS = 8

  // access flags 0x8
  static printArray([I)V
   L0
    LINENUMBER 53 L0
    ALOAD 0
    ARRAYLENGTH
    ISTORE 1
   L1
    LINENUMBER 54 L1
    ICONST_0
    ISTORE 2
   L2
   FRAME APPEND [I I]
    ILOAD 2
    ILOAD 1
    IF_ICMPGE L3
   L4
    LINENUMBER 55 L4
    GETSTATIC java/lang/System.out : Ljava/io/PrintStream;
    ALOAD 0
    ILOAD 2
    IALOAD
    INVOKEDYNAMIC makeConcatWithConstants(I)Ljava/lang/String; [
      // handle kind 0x6 : INVOKESTATIC
      java/lang/invoke/StringConcatFactory.makeConcatWithConstants(Ljava/lang/invoke/MethodHandles$Lookup;Ljava/lang/String;Ljava/lang/invoke/MethodType;Ljava/lang/String;[Ljava/lang/Object;)Ljava/lang/invoke/CallSite;
      // arguments:
      "\u0001 "
    ]
    INVOKEVIRTUAL java/io/PrintStream.print (Ljava/lang/String;)V
   L5
    LINENUMBER 54 L5
    IINC 2 1
    GOTO L2
   L3
    LINENUMBER 56 L3
   FRAME CHOP 1
    GETSTATIC java/lang/System.out : Ljava/io/PrintStream;
    INVOKEVIRTUAL java/io/PrintStream.println ()V
   L6
    LINENUMBER 57 L6
    RETURN
   L7
    LOCALVARIABLE i I L2 L3 2
    LOCALVARIABLE arr [I L0 L7 0
    LOCALVARIABLE n I L1 L7 1
    MAXSTACK = 3
    MAXLOCALS = 3

  // access flags 0x9
  public static main([Ljava/lang/String;)V
   L0
    LINENUMBER 62 L0
    BIPUSH 6
    NEWARRAY T_INT
    DUP
    ICONST_0
    BIPUSH 12
    IASTORE
    DUP
    ICONST_1
    BIPUSH 11
    IASTORE
    DUP
    ICONST_2
    BIPUSH 13
    IASTORE
    DUP
    ICONST_3
    ICONST_5
    IASTORE
    DUP
    ICONST_4
    BIPUSH 6
    IASTORE
    DUP
    ICONST_5
    BIPUSH 7
    IASTORE
    ASTORE 1
   L1
    LINENUMBER 63 L1
    ALOAD 1
    ARRAYLENGTH
    ISTORE 2
   L2
    LINENUMBER 65 L2
    NEW HeapSort
    DUP
    INVOKESPECIAL HeapSort.<init> ()V
    ASTORE 3
   L3
    LINENUMBER 66 L3
    ALOAD 3
    ALOAD 1
    INVOKEVIRTUAL HeapSort.sort ([I)V
   L4
    LINENUMBER 68 L4
    GETSTATIC java/lang/System.out : Ljava/io/PrintStream;
    LDC "Sorted array is"
    INVOKEVIRTUAL java/io/PrintStream.println (Ljava/lang/String;)V
   L5
    LINENUMBER 69 L5
    ALOAD 1
    INVOKESTATIC HeapSort.printArray ([I)V
   L6
    LINENUMBER 70 L6
    RETURN
   L7
    LOCALVARIABLE args [Ljava/lang/String; L0 L7 0
    LOCALVARIABLE arr [I L1 L7 1
    LOCALVARIABLE n I L2 L7 2
    LOCALVARIABLE ob LHeapSort; L3 L7 3
    MAXSTACK = 4
    MAXLOCALS = 4
}
